README.rst
setup.py
bidso/VERSION
bidso/__init__.py
bidso/directories.py
bidso/files.py
bidso/find.py
bidso/objects.py
bidso/utils.py
bidso.egg-info/PKG-INFO
bidso.egg-info/SOURCES.txt
bidso.egg-info/dependency_links.txt
bidso.egg-info/requires.txt
bidso.egg-info/top_level.txt
bidso/derivatives/__init__.py